oxidl/__init__.py
oxidl-0.0.1.dist-info/METADATA
oxidl-0.0.1.dist-info/WHEEL
oxidl-0.0.1.dist-info/RECORD
