Metadata-Version: 2.4
Name: oxidl
Version: 0.0.1
Summary: Fast parallel downloads with slab-based memory control
License: MIT
Requires-Python: >=3.8
